dit_activity_stream/__init__.py
dit_activity_stream/client.py
dit_activity_stream/py.typed
dit_activity_stream/test_app/__init__.py
dit_activity_stream/test_app/apps.py
dit_activity_stream/test_app/client.py
dit_activity_stream/test_app/factories.py
dit_activity_stream/test_app/models.py
dit_activity_stream/test_app/settings.py
dit_activity_stream/test_app/urls.py
dit_activity_stream/test_app/utils.py
dit_activity_stream/tests/__init__.py
dit_activity_stream/tests/test_client.py
dit_activity_stream/tests/test_views.py
dit_activity_stream/urls.py
dit_activity_stream/views.py
dit_activity_stream-0.2.5.dist-info/LICENSE
dit_activity_stream-0.2.5.dist-info/METADATA
dit_activity_stream-0.2.5.dist-info/WHEEL
dit_activity_stream-0.2.5.dist-info/RECORD
