Metadata-Version: 2.1
Name: dit-activity-stream
Version: 0.2.5
Summary: DIT Activity Stream
Home-page: https://github.com/uktrade/dit-activity-stream
License: MIT
Keywords: django
Author: Cameron Lamb
Author-email: live.services@digital.trade.gov.uk
Requires-Python: >=3.10,<4.0
Classifier: License :: OSI Approved :: MIT License
Classifier: Programming Language :: Python :: 3
Classifier: Programming Language :: Python :: 3.10
Classifier: Programming Language :: Python :: 3.11
Classifier: Programming Language :: Python :: 3.12
Requires-Dist: django (>=3.2,<6)
Requires-Dist: django-hawk (>=1.2.3,<2.0.0)
